srslyumi/__init__.py
srslyumi/bamtag.py
srslyumi/cli.py
srslyumi/tests/__init__.py
srslyumi/tests/test_bamtag.py
srslyumi/tests/test_cli.py
srslyumi-0.4.dist-info/LICENSE
srslyumi-0.4.dist-info/METADATA
srslyumi-0.4.dist-info/WHEEL
srslyumi-0.4.dist-info/entry_points.txt
srslyumi-0.4.dist-info/top_level.txt
srslyumi-0.4.dist-info/RECORD
