Metadata-Version: 2.1
Name: srslyumi
Version: 0.4
Summary: process SRSLY UMIs
Home-page: https://github.com/claretbio/SRSLYumi
Author: Charles Vaske
Author-email: charles.vaske@claretbio.com
License: UNKNOWN
Platform: UNKNOWN
Classifier: Programming Language :: Python :: 2
Classifier: Programming Language :: Python :: 3
Classifier: License :: OSI Approved :: MIT License
Classifier: Operating System :: OS Independent
Classifier: Topic :: Scientific/Engineering :: Bio-Informatics
Requires-Python: >=2.7
Requires-Dist: pysam (>=0.15.3)
